OrangeARFF/ARFFReader.py
OrangeARFF/__init__.py
OrangeARFF-1.0.3.dist-info/LICENSE
OrangeARFF-1.0.3.dist-info/METADATA
OrangeARFF-1.0.3.dist-info/WHEEL
OrangeARFF-1.0.3.dist-info/entry_points.txt
OrangeARFF-1.0.3.dist-info/top_level.txt
OrangeARFF-1.0.3.dist-info/RECORD
