Metadata-Version: 2.1
Name: OrangeARFF
Version: 1.0.3
Summary: AFFF add-on for Orange 3 Orange.data.io mining software.
Home-page: https://github.com/gualbe/Orange-ARFF
Author: Gualberto Asencio Cortés
Author-email: guaasecor@upo.es
License: GPL3+
Keywords: orange3 add-on,OrangeARFF,Orange.data.io mining,orange,addon
Classifier: Development Status :: 4 - Beta
Classifier: Environment :: Plugins
Classifier: Programming Language :: Python
Classifier: License :: OSI Approved :: GNU General Public License v3 or later (GPLv3+)
Classifier: Operating System :: OS Independent
Classifier: Topic :: Software Development :: Libraries :: Python Modules
Classifier: Intended Audience :: Education
Classifier: Intended Audience :: Science/Research
Classifier: Intended Audience :: Developers
License-File: LICENSE
